{
    "api": {
        "results": 14,
        "fixtures": {
            "3858": {
                "fixture_id": "3858",
                "event_timestamp": "1547650800",
                "event_date": "2019-01-16T15:00:00+00:00",
                "league_id": "12",
                "round": "Ligapro - 14",
                "homeTeam_id": "229",
                "awayTeam_id": "238",
                "homeTeam": "Benfica B",
                "awayTeam": "Academico Viseu",
                "status": "Not Started",
                "statusShort": "NS",
                "goalsHomeTeam": "",
                "goalsAwayTeam": "",
                "halftime_score": null,
                "final_score": null,
                "penalty": null,
                "elapsed": "0",
                "firstHalfStart": "0",
                "secondHalfStart": "0"
            },
            "30665": {
                "fixture_id": "30665",
                "event_timestamp": "1547628600",
                "event_date": "2019-01-16T08:50:00+00:00",
                "league_id": "105",
                "round": "A-League - 12",
                "homeTeam_id": "941",
                "awayTeam_id": "945",
                "homeTeam": "Central Coast Mariners FC",
                "awayTeam": "Melbourne City",
                "status": "Not Started",
                "statusShort": "NS",
                "goalsHomeTeam": null,
                "goalsAwayTeam": null,
                "halftime_score": null,
                "final_score": null,
                "penalty": null,
                "elapsed": "0",
                "firstHalfStart": "0",
                "secondHalfStart": "0"
            },
            "37716": {
                "fixture_id": "37716",
                "event_timestamp": "1547661600",
                "event_date": "2019-01-16T18:00:00+00:00",
                "league_id": "4",
                "round": "Ligue 1 - 17",
                "homeTeam_id": "91",
                "awayTeam_id": "84",
                "homeTeam": "Monaco",
                "awayTeam": "Nice",
                "status": "Not Started",
                "statusShort": "NS",
                "goalsHomeTeam": null,
                "goalsAwayTeam": null,
                "halftime_score": "-",
                "final_score": null,
                "penalty": null,
                "elapsed": "0",
                "firstHalfStart": "0",
                "secondHalfStart": "0"
            },
            "37717": {
                "fixture_id": "37717",
                "event_timestamp": "1547661600",
                "event_date": "2019-01-16T18:00:00+00:00",
                "league_id": "4",
                "round": "Ligue 1 - 17",
                "homeTeam_id": "92",
                "awayTeam_id": "83",
                "homeTeam": "Nimes",
                "awayTeam": "Nantes",
                "status": "Not Started",
                "statusShort": "NS",
                "goalsHomeTeam": null,
                "goalsAwayTeam": null,
                "halftime_score": "-",
                "final_score": null,
                "penalty": null,
                "elapsed": "0",
                "firstHalfStart": "0",
                "secondHalfStart": "0"
            },
            "37720": {
                "fixture_id": "37720",
                "event_timestamp": "1547668800",
                "event_date": "2019-01-16T20:00:00+00:00",
                "league_id": "4",
                "round": "Ligue 1 - 17",
                "homeTeam_id": "1063",
                "awayTeam_id": "81",
                "homeTeam": "Saint Etienne",
                "awayTeam": "Marseille",
                "status": "Not Started",
                "statusShort": "NS",
                "goalsHomeTeam": null,
                "goalsAwayTeam": null,
                "halftime_score": "-",
                "final_score": null,
                "penalty": null,
                "elapsed": "0",
                "firstHalfStart": "0",
                "secondHalfStart": "0"
            },
            "37722": {
                "fixture_id": "37722",
                "event_timestamp": "1547661600",
                "event_date": "2019-01-16T18:00:00+00:00",
                "league_id": "4",
                "round": "Ligue 1 - 17",
                "homeTeam_id": "96",
                "awayTeam_id": "80",
                "homeTeam": "Toulouse",
                "awayTeam": "Lyon",
                "status": "Not Started",
                "statusShort": "NS",
                "goalsHomeTeam": null,
                "goalsAwayTeam": null,
                "halftime_score": "-",
                "final_score": null,
                "penalty": null,
                "elapsed": "0",
                "firstHalfStart": "0",
                "secondHalfStart": "0"
            },
            "37726": {
                "fixture_id": "37726",
                "event_timestamp": "1547661600",
                "event_date": "2019-01-16T18:00:00+00:00",
                "league_id": "4",
                "round": "Ligue 1 - 18",
                "homeTeam_id": "90",
                "awayTeam_id": "94",
                "homeTeam": "Guingamp",
                "awayTeam": "Rennes",
                "status": "Not Started",
                "statusShort": "NS",
                "goalsHomeTeam": null,
                "goalsAwayTeam": null,
                "halftime_score": "-",
                "final_score": null,
                "penalty": null,
                "elapsed": "0",
                "firstHalfStart": "0",
                "secondHalfStart": "0"
            },
            "39723": {
                "fixture_id": "39723",
                "event_timestamp": "1547647200",
                "event_date": "2019-01-16T14:00:00+00:00",
                "league_id": "115",
                "round": "Botola Pro - 14",
                "homeTeam_id": "976",
                "awayTeam_id": "965",
                "homeTeam": "Raja Casablanca",
                "awayTeam": "Moghreb Tetouan",
                "status": "Not Started",
                "statusShort": "NS",
                "goalsHomeTeam": null,
                "goalsAwayTeam": null,
                "halftime_score": "-",
                "final_score": null,
                "penalty": null,
                "elapsed": "0",
                "firstHalfStart": "0",
                "secondHalfStart": "0"
            },
            "55752": {
                "fixture_id": "55752",
                "event_timestamp": "1547645400",
                "event_date": "2019-01-16T13:30:00+00:00",
                "league_id": "195",
                "round": "Asian Cup Grp. C - Matchday 3",
                "homeTeam_id": "1554",
                "awayTeam_id": "1555",
                "homeTeam": "Kyrgyzstan",
                "awayTeam": "Philippines",
                "status": "Not Started",
                "statusShort": "NS",
                "goalsHomeTeam": null,
                "goalsAwayTeam": null,
                "halftime_score": "-",
                "final_score": null,
                "penalty": null,
                "elapsed": "0",
                "firstHalfStart": "0",
                "secondHalfStart": "0"
            },
            "55753": {
                "fixture_id": "55753",
                "event_timestamp": "1547645400",
                "event_date": "2019-01-16T13:30:00+00:00",
                "league_id": "195",
                "round": "Asian Cup Grp. C - Matchday 3",
                "homeTeam_id": "17",
                "awayTeam_id": "1566",
                "homeTeam": "South Korea",
                "awayTeam": "China",
                "status": "Not Started",
                "statusShort": "NS",
                "goalsHomeTeam": null,
                "goalsAwayTeam": null,
                "halftime_score": "-",
                "final_score": null,
                "penalty": null,
                "elapsed": "0",
                "firstHalfStart": "0",
                "secondHalfStart": "0"
            },
            "55754": {
                "fixture_id": "55754",
                "event_timestamp": "1547654400",
                "event_date": "2019-01-16T16:00:00+00:00",
                "league_id": "195",
                "round": "Asian Cup Grp. D - Matchday 3",
                "homeTeam_id": "22",
                "awayTeam_id": "1567",
                "homeTeam": "Iran",
                "awayTeam": "Iraq",
                "status": "Not Started",
                "statusShort": "NS",
                "goalsHomeTeam": null,
                "goalsAwayTeam": null,
                "halftime_score": "-",
                "final_score": null,
                "penalty": null,
                "elapsed": "0",
                "firstHalfStart": "0",
                "secondHalfStart": "0"
            },
            "55755": {
                "fixture_id": "55755",
                "event_timestamp": "1547654400",
                "event_date": "2019-01-16T16:00:00+00:00",
                "league_id": "195",
                "round": "Asian Cup Grp. D - Matchday 3",
                "homeTeam_id": "1542",
                "awayTeam_id": "1550",
                "homeTeam": "Vietnam",
                "awayTeam": "Yemen",
                "status": "Not Started",
                "statusShort": "NS",
                "goalsHomeTeam": null,
                "goalsAwayTeam": null,
                "halftime_score": "-",
                "final_score": null,
                "penalty": null,
                "elapsed": "0",
                "firstHalfStart": "0",
                "secondHalfStart": "0"
            },
            "60190": {
                "fixture_id": "60190",
                "event_timestamp": "1547645400",
                "event_date": "2019-01-16T13:30:00+00:00",
                "league_id": "210",
                "round": "Serie C Group C - Round 3",
                "homeTeam_id": "1585",
                "awayTeam_id": "880",
                "homeTeam": "Viterbese",
                "awayTeam": "Reggiana",
                "status": "Not Started",
                "statusShort": "NS",
                "goalsHomeTeam": "",
                "goalsAwayTeam": "",
                "halftime_score": null,
                "final_score": null,
                "penalty": null,
                "elapsed": "0",
                "firstHalfStart": "0",
                "secondHalfStart": "0"
            },
            "69840": {
                "fixture_id": "69840",
                "event_timestamp": "1547643600",
                "event_date": "2019-01-16T13:00:00+00:00",
                "league_id": "116",
                "round": "Ligue Professionnelle 1 - Round 12",
                "homeTeam_id": "987",
                "awayTeam_id": "983",
                "homeTeam": "AS Gabes",
                "awayTeam": "CS Sfaxien",
                "status": "Not Started",
                "statusShort": "NS",
                "goalsHomeTeam": null,
                "goalsAwayTeam": null,
                "halftime_score": "-",
                "final_score": null,
                "penalty": null,
                "elapsed": "0",
                "firstHalfStart": "0",
                "secondHalfStart": "0"
            }
        }
    }
}